synthale/__init__.py
synthale/cli.py
synthale/convert.py
synthale/markdown.py
synthale/recipes.py
synthale-0.1.1.dist-info/LICENSE
synthale-0.1.1.dist-info/METADATA
synthale-0.1.1.dist-info/WHEEL
synthale-0.1.1.dist-info/entry_points.txt
synthale-0.1.1.dist-info/top_level.txt
synthale-0.1.1.dist-info/RECORD
