Metadata-Version: 2.1
Name: synthale
Version: 0.1.1
Summary: Synthale is a command line tool that convert BeerXML files into Markdown files.
Home-page: https://github.com/shouptech/synthale
Author: Mike Shoup
Author-email: mike@shoup.io
License: UNKNOWN
Platform: UNKNOWN
Classifier: Development Status :: 4 - Beta
Classifier: Environment :: Console
Classifier: License :: OSI Approved :: GNU General Public License v3 (GPLv3)
Classifier: Natural Language :: English
Classifier: Operating System :: OS Independent
Classifier: Programming Language :: Python :: 3.5
Classifier: Programming Language :: Python :: 3.6
Classifier: Programming Language :: Python :: 3.7
Classifier: Programming Language :: Python :: 3 :: Only
Classifier: Topic :: Internet :: WWW/HTTP
Classifier: Topic :: Software Development :: Libraries :: Python Modules
Requires-Dist: Click
Requires-Dist: pybeerxml (>=1.0.6)
